<?xml version="1.0" encoding="UTF-8"?>
<databaseChangeLog xmlns="http://www.liquibase.org/xml/ns/dbchangelog"
                   xmlns:xsi="http://www.w3.org/2001/XMLSchema-instance"
                   xsi:schemaLocation="http://www.liquibase.org/xml/ns/dbchangelog
                   https://www.liquibase.org/xml/ns/dbchangelog/dbchangelog-latest.xsd">

    <changeSet id="1" author="admin">
        <sqlFile path="db/changelog/1.0/create-car-table.sql"/>
        <rollback>
            <dropTable tableName="car"/>
        </rollback>
    </changeSet>
    <changeSet id="2" author="admin">
        <sqlFile path="db/changelog/1.0/insert-car-table.sql"/>
    </changeSet>
    <changeSet id="3" author="admin">
        <sqlFile path="db/changelog/1.0/create-owner-table.sql"/>
            <rollback>
                <dropTable tableName="owner"/>
            </rollback>
    </changeSet>
    <changeSet id="4" author="admin">
        <sqlFile path="db/changelog/1.0/create-car-owner-table.sql"/>
    </changeSet>
    <changeSet id="5" author="admin">
        <sqlFile path="db/changelog/1.0/insert-owner-table.sql"/>
    </changeSet>
</databaseChangeLog>